big_fiubrother_detection/__init__.py
big_fiubrother_detection/face_detector_caffe_mtcnn.py
big_fiubrother_detection/face_detector_factory.py
big_fiubrother_detection/face_detector_movidius_mtcnn.py
big_fiubrother_detection/face_detector_movidius_ssd.py
big_fiubrother_detection/face_detector_thread.py
big_fiubrother_detection/config/config_caffe_mtcnn.yaml
big_fiubrother_detection/config/config_mvds_mtcnn.yaml
big_fiubrother_detection/config/config_mvds_ssd.yaml
big_fiubrother_detection/config/config_mvds_ssd_longrange.yaml
big_fiubrother_detection/model/onet.caffemodel
big_fiubrother_detection/model/onet.graph
big_fiubrother_detection/model/onet.png
big_fiubrother_detection/model/onet.prototxt
big_fiubrother_detection/model/pnet.caffemodel
big_fiubrother_detection/model/pnet.graph
big_fiubrother_detection/model/pnet.png
big_fiubrother_detection/model/pnet.prototxt
big_fiubrother_detection/model/rnet.caffemodel
big_fiubrother_detection/model/rnet.png
big_fiubrother_detection/model/rnet.prototxt
big_fiubrother_detection/model/ssd.graph
big_fiubrother_detection/model/ssd_longrange.graph
big_fiubrother_detection-0.1.6.data/scripts/big_fiubrother_detection_demo_files.py
big_fiubrother_detection-0.1.6.data/scripts/big_fiubrother_detection_demo_webcam.py
big_fiubrother_detection-0.1.6.data/scripts/big_fiubrother_detection_output_compare.py
big_fiubrother_detection-0.1.6.dist-info/METADATA
big_fiubrother_detection-0.1.6.dist-info/RECORD
big_fiubrother_detection-0.1.6.dist-info/WHEEL
big_fiubrother_detection-0.1.6.dist-info/top_level.txt
