Metadata-Version: 2.1
Name: big-fiubrother-detection
Version: 0.1.6
Summary: Big Fiubrother Face Detection application
Home-page: https://github.com/BigFiuBrother/big-fiubrother-detection
Author: Eduardo Neira, Gabriel Gayoso
Author-email: gabriel.gayoso@fi.uba.ar
License: GPLv3
Platform: UNKNOWN
Requires-Dist: opencv-python
Requires-Dist: numpy
Requires-Dist: pyyaml
